ntiles/__init__.py
ntiles/ntile_kicker.py
ntiles/periods.py
ntiles/plotter.py
ntiles/stats.py
ntiles/utils.py
ntiles/portals/__init__.py
ntiles/portals/base_portal.py
ntiles/portals/equity_db_pricing_portal.py
ntiles/portals/equity_db_sector_portal.py
ntiles/portals/pricing_portal.py
ntiles/portals/sector_portal.py
ntiles/tears/__init__.py
ntiles/tears/backtest_tear.py
ntiles/tears/base_tear.py
ntiles/tears/ic_tear.py
ntiles/tears/inspection_tear.py
ntiles/tears/tilts_backtest_tear.py
ntiles/tears/turnover_tear.py
ntiles-0.1.5.1.dist-info/LICENSE.txt
ntiles-0.1.5.1.dist-info/METADATA
ntiles-0.1.5.1.dist-info/WHEEL
ntiles-0.1.5.1.dist-info/top_level.txt
ntiles-0.1.5.1.dist-info/RECORD
