Metadata-Version: 2.1
Name: ntiles
Version: 0.1.5.1
Summary: Vectorized quantile backtester.
Home-page: https://github.com/Alexd14/ntiles-backtester
Author: UNKNOWN
Author-email: UNKNOWN
License: Apache License 2.0
Download-URL: https://github.com/Alexd14/ntiles/archive/refs/tags/v1.5.1.tar.gz
Keywords: factor,backtesting,alphalens,vectorized backtesting,equity trading
Platform: UNKNOWN
Classifier: License :: OSI Approved :: Apache Software License
Classifier: Programming Language :: Python :: 3.7
Classifier: Programming Language :: Python :: 3.8
Classifier: Programming Language :: Python :: 3.9
Classifier: Programming Language :: Python :: 3.10
Requires-Dist: numba
Requires-Dist: pandas
Requires-Dist: numpy
Requires-Dist: matplotlib
Requires-Dist: empyrical
Requires-Dist: factor-toolbox
